{"items": [{"str": "m", "x1": 0, "y1": 0, "x2": 639, "y2": 415}, {"str": "n", "x1": 572, "y1": 43, "x2": 588, "y2": 66}, {"str": "n", "x1": 359, "y1": 44, "x2": 376, "y2": 67}, {"str": "7", "x1": 385, "y1": 44, "x2": 393, "y2": 51}, {"str": "n", "x1": 422, "y1": 44, "x2": 441, "y2": 67}, {"str": "a", "x1": 469, "y1": 44, "x2": 488, "y2": 66}, {"str": ",", "x1": 494, "y1": 44, "x2": 500, "y2": 67}, {"str": "h", "x1": 521, "y1": 44, "x2": 539, "y2": 66}, {"str": "a", "x1": 545, "y1": 44, "x2": 565, "y2": 66}, {"str": "0", "x1": 596, "y1": 44, "x2": 612, "y2": 66}, {"str": "m", "x1": 310, "y1": 45, "x2": 327, "y2": 67}, {"str": ",", "x1": 358, "y1": 45, "x2": 364, "y2": 68}, {"str": "k", "x1": 384, "y1": 45, "x2": 401, "y2": 67}, {"str": ",", "x1": 468, "y1": 61, "x2": 473, "y2": 67}, {"str": "9", "x1": 205, "y1": 232, "x2": 221, "y2": 260}, {"str": "8", "x1": 233, "y1": 232, "x2": 248, "y2": 261}, {"str": "0", "x1": 259, "y1": 232, "x2": 276, "y2": 261}, {"str": "9", "x1": 339, "y1": 232, "x2": 355, "y2": 259}, {"str": "0", "x1": 366, "y1": 232, "x2": 383, "y2": 260}, {"str": "0", "x1": 96, "y1": 233, "x2": 113, "y2": 261}, {"str": "8", "x1": 151, "y1": 233, "x2": 167, "y2": 261}, {"str": "r", "x1": 503, "y1": 233, "x2": 515, "y2": 244}, {"str": "r", "x1": 530, "y1": 233, "x2": 542, "y2": 244}, {"str": "9", "x1": 556, "y1": 233, "x2": 573, "y2": 260}, {"str": "m", "x1": 342, "y1": 235, "x2": 352, "y2": 245}, {"str": "0", "x1": 369, "y1": 235, "x2": 379, "y2": 257}, {"str": "4", "x1": 475, "y1": 235, "x2": 490, "y2": 260}, {"str": "4", "x1": 69, "y1": 236, "x2": 85, "y2": 261}, {"str": "m", "x1": 208, "y1": 236, "x2": 218, "y2": 246}, {"str": "n", "x1": 262, "y1": 236, "x2": 272, "y2": 257}, {"str": "m", "x1": 559, "y1": 236, "x2": 569, "y2": 246}, {"str": "n", "x1": 99, "y1": 237, "x2": 110, "y2": 258}, {"str": "n", "x1": 156, "y1": 237, "x2": 163, "y2": 242}, {"str": ",", "x1": 505, "y1": 237, "x2": 511, "y2": 242}, {"str": "0", "x1": 421, "y1": 238, "x2": 437, "y2": 260}, {"str": ",", "x1": 426, "y1": 241, "x2": 436, "y2": 246}, {"str": "7", "x1": 504, "y1": 244, "x2": 517, "y2": 260}, {"str": "7", "x1": 531, "y1": 244, "x2": 544, "y2": 258}, {"str": "m", "x1": 424, "y1": 247, "x2": 434, "y2": 256}, {"str": "m", "x1": 235, "y1": 248, "x2": 245, "y2": 257}, {"str": "m", "x1": 154, "y1": 249, "x2": 164, "y2": 258}, {"str": ",", "x1": 475, "y1": 255, "x2": 485, "y2": 260}, {"str": "x", "x1": 86, "y1": 283, "x2": 103, "y2": 295}, {"str": "m", "x1": 461, "y1": 288, "x2": 617, "y2": 360}, {"str": "x", "x1": 250, "y1": 289, "x2": 258, "y2": 295}, {"str": "m", "x1": 266, "y1": 299, "x2": 278, "y2": 306}, {"str": "m", "x1": 257, "y1": 300, "x2": 263, "y2": 306}, {"str": "0", "x1": 322, "y1": 303, "x2": 334, "y2": 323}, {"str": "7", "x1": 400, "y1": 304, "x2": 408, "y2": 313}, {"str": "v", "x1": 473, "y1": 304, "x2": 518, "y2": 344}, {"str": "f", "x1": 519, "y1": 305, "x2": 534, "y2": 344}, {"str": "5", "x1": 536, "y1": 305, "x2": 565, "y2": 344}, {"str": "a", "x1": 566, "y1": 305, "x2": 600, "y2": 344}, {"str": "u", "x1": 343, "y1": 316, "x2": 353, "y2": 322}, {"str": "+", "x1": 399, "y1": 318, "x2": 410, "y2": 323}, {"str": "x", "x1": 227, "y1": 336, "x2": 235, "y2": 343}, {"str": "7", "x1": 247, "y1": 336, "x2": 254, "y2": 350}, {"str": ",", "x1": 321, "y1": 336, "x2": 326, "y2": 351}, {"str": "y", "x1": 337, "y1": 336, "x2": 347, "y2": 353}, {"str": "0", "x1": 53, "y1": 337, "x2": 62, "y2": 353}, {"str": "m", "x1": 70, "y1": 337, "x2": 81, "y2": 354}, {"str": "1", "x1": 92, "y1": 337, "x2": 98, "y2": 352}, {"str": "1", "x1": 109, "y1": 337, "x2": 119, "y2": 354}, {"str": "r", "x1": 128, "y1": 337, "x2": 139, "y2": 354}, {"str": "t", "x1": 224, "y1": 337, "x2": 233, "y2": 353}, {"str": "6", "x1": 243, "y1": 337, "x2": 252, "y2": 354}, {"str": "k", "x1": 299, "y1": 337, "x2": 311, "y2": 354}, {"str": "4", "x1": 280, "y1": 338, "x2": 290, "y2": 351}, {"str": "1", "x1": 109, "y1": 339, "x2": 114, "y2": 355}, {"str": ",", "x1": 284, "y1": 339, "x2": 290, "y2": 346}, {"str": ",", "x1": 305, "y1": 344, "x2": 311, "y2": 351}, {"str": "+", "x1": 281, "y1": 346, "x2": 288, "y2": 353}, {"str": "r", "x1": 302, "y1": 348, "x2": 310, "y2": 354}]}